bliss_audio-0.1.11.dist-info/METADATA
bliss_audio-0.1.11.dist-info/WHEEL
bliss_audio/__init__.py
bliss_audio/bliss_audio.cpython-310-x86_64-linux-gnu.so
bliss_audio-0.1.11.dist-info/RECORD
