Metadata-Version: 2.1
Name: bliss_audio
Version: 0.1.11
Classifier: Programming Language :: Python :: 3
Classifier: License :: OSI Approved :: MIT License
Classifier: Operating System :: OS Independent
Summary: A package containing helpers to make audio playlists.
Author: Polochon-street <polochonstreet@gmx.fr>
Author-email: Polochon_street <polochonstreet@gmx.feature>
Requires-Python: >=3.7
Project-URL: Homepage, https://github.com/Polochon-street/bliss-rs
Project-URL: Issues, https://github.com/Polochon-street/bliss-rs/issues
